Metadata-Version: 2.4
Name: kestrel
Version: 0.0.2
Summary: a fast, efficient inference engine for moondream
Requires-Python: >=3.10
License-File: LICENSE.md
Requires-Dist: torch==2.9.1
Requires-Dist: kestrel-kernels==0.1.0
Requires-Dist: tokenizers>=0.15
Requires-Dist: safetensors>=0.4
Requires-Dist: transformers>=4.44
Requires-Dist: pyvips>=2.3
Requires-Dist: pyvips-binary>=2.48
Requires-Dist: pillow>=10
Requires-Dist: torch-c-dlpack-ext>=0.1.3
Requires-Dist: starlette>=0.37
Requires-Dist: httpx>=0.27
Requires-Dist: uvicorn>=0.30
Requires-Dist: flashinfer-python>=0.6.0
Requires-Dist: opencv-python-headless>=4.5
Requires-Dist: pypotrace==0.3
Requires-Dist: resvg>=0.1.2
Requires-Dist: apache-tvm-ffi<0.2,>=0.1.5
Provides-Extra: dev
Requires-Dist: pytest>=8.0; extra == "dev"
Provides-Extra: eval
Requires-Dist: datasets>=3.0; extra == "eval"
Requires-Dist: tqdm>=4.66; extra == "eval"
Dynamic: license-file
